cube_rs-0.1.0.dist-info/METADATA
cube_rs-0.1.0.dist-info/WHEEL
cube_rs.libs/libgcc_s-b5472b99.so.1
cube_rs/__init__.py
cube_rs/cube_rs.cpython-38-i386-linux-gnu.so
cube_rs-0.1.0.dist-info/RECORD
